Py_dm/__init__.py
Py_dm/leidian.py
Py_dm/mouse.py
Py_dm/pic.py
Py_dm/regserdm.py
Py_dm/string.py
Py_dm/window.py
Py_dm-0.0.2.dist-info/LICENSE.txt
Py_dm-0.0.2.dist-info/METADATA
Py_dm-0.0.2.dist-info/WHEEL
Py_dm-0.0.2.dist-info/top_level.txt
Py_dm-0.0.2.dist-info/RECORD
